<annotation><folder>VOC2012</folder><filename>16418132831_c7bdf657b6_k.jpg</filename><source><database>The VOC2007 Database</database><annotation>PASCAL VOC2007</annotation><image>flickr</image></source><size><width>1920</width><height>960</height><depth>3</depth></size><segmented>0</segmented><object><name>light</name><pose>Unspecified</pose><truncated>0</truncated><difficult>0</difficult><bndbox><x_center>312</x_center><y_center>259</y_center><phi>-2.1222112873468553</phi><theta>0.724857054968895</theta><w>4</w><h>4</h></bndbox></object><object><name>light</name><pose>Unspecified</pose><truncated>0</truncated><difficult>0</difficult><bndbox><x_center>409</x_center><y_center>241</y_center><phi>-1.8047795296403863</phi><theta>0.7837619172237035</theta><w>4</w><h>4</h></bndbox></object><object><name>light</name><pose>Unspecified</pose><truncated>0</truncated><difficult>0</difficult><bndbox><x_center>596</x_center><y_center>248</y_center><phi>-1.1928234606598744</phi><theta>0.760854470791278</theta><w>4</w><h>4</h></bndbox></object><object><name>light</name><pose>Unspecified</pose><truncated>0</truncated><difficult>0</difficult><bndbox><x_center>672</x_center><y_center>264</y_center><phi>-0.9441140422506826</phi><theta>0.7084945932314481</theta><w>4</w><h>4</h></bndbox></object><object><name>light</name><pose>Unspecified</pose><truncated>0</truncated><difficult>0</difficult><bndbox><x_center>750</x_center><y_center>306</y_center><phi>-0.6888596391465118</phi><theta>0.5710499146368947</theta><w>4</w><h>4</h></bndbox></object><object><name>light</name><pose>Unspecified</pose><truncated>0</truncated><difficult>0</difficult><bndbox><x_center>790</x_center><y_center>329</y_center><phi>-0.5579599452469373</phi><theta>0.4957825906446393</theta><w>4</w><h>4</h></bndbox></object><object><name>light</name><pose>Unspecified</pose><truncated>0</truncated><difficult>0</difficult><bndbox><x_center>861</x_center><y_center>375</y_center><phi>-0.32561298857519205</phi><theta>0.34524794266012837</theta><w>4</w><h>4</h></bndbox></object><object><name>light</name><pose>Unspecified</pose><truncated>0</truncated><difficult>0</difficult><bndbox><x_center>901</x_center><y_center>369</y_center><phi>-0.1947132946756175</phi><theta>0.3648828967450645</theta><w>4</w><h>4</h></bndbox></object><object><name>light</name><pose>Unspecified</pose><truncated>0</truncated><difficult>0</difficult><bndbox><x_center>821</x_center><y_center>356</y_center><phi>-0.4565126824747667</phi><theta>0.4074252972624263</theta><w>4</w><h>4</h></bndbox></object><object><name>light</name><pose>Unspecified</pose><truncated>0</truncated><difficult>0</difficult><bndbox><x_center>1499</x_center><y_center>248</y_center><phi>1.7622371291230248</phi><theta>0.760854470791278</theta><w>4</w><h>4</h></bndbox></object><object><name>light</name><pose>Unspecified</pose><truncated>0</truncated><difficult>0</difficult><bndbox><x_center>1591</x_center><y_center>265</y_center><phi>2.0633064250920463</phi><theta>0.7052221008839588</theta><w>4</w><h>4</h></bndbox></object><object><name>light</name><pose>Unspecified</pose><truncated>0</truncated><difficult>0</difficult><bndbox><x_center>1657</x_center><y_center>284</y_center><phi>2.279290920026345</phi><theta>0.6430447462816609</theta><w>4</w><h>4</h></bndbox></object><object><name>light</name><pose>Unspecified</pose><truncated>0</truncated><difficult>0</difficult><bndbox><x_center>1337</x_center><y_center>254</y_center><phi>1.2320933688297466</phi><theta>0.7412195167063419</theta><w>4</w><h>4</h></bndbox></object><object><name>light</name><pose>Unspecified</pose><truncated>0</truncated><difficult>0</difficult><bndbox><x_center>1258</x_center><y_center>275</y_center><phi>0.9735664733780867</phi><theta>0.672497177409065</theta><w>4</w><h>4</h></bndbox></object><object><name>sofa</name><pose>Unspecified</pose><truncated>0</truncated><difficult>0</difficult><bndbox><x_center>1912</x_center><y_center>521</y_center><phi>3.1137764686361336</phi><theta>-0.13253594007331954</theta><w>12</w><h>8</h></bndbox></object><object><name>chair</name><pose>Unspecified</pose><truncated>0</truncated><difficult>0</difficult><bndbox><x_center>181</x_center><y_center>510</y_center><phi>-2.550907784867962</phi><theta>-0.09653852425093644</theta><w>4</w><h>8</h></bndbox></object><object><name>chair</name><pose>Unspecified</pose><truncated>0</truncated><difficult>0</difficult><bndbox><x_center>60</x_center><y_center>526</y_center><phi>-2.9468793589141757</phi><theta>-0.14889840181076613</theta><w>4</w><h>8</h></bndbox></object><object><name>chair</name><pose>Unspecified</pose><truncated>0</truncated><difficult>0</difficult><bndbox><x_center>1873</x_center><y_center>569</y_center><phi>2.986149267084048</phi><theta>-0.28961557275280897</theta><w>12</w><h>12</h></bndbox></object><object><name>window</name><pose>Unspecified</pose><truncated>0</truncated><difficult>0</difficult><bndbox><x_center>257</x_center><y_center>392</y_center><phi>-2.30219836645877</phi><theta>0.28961557275280897</theta><w>20</w><h>52</h></bndbox></object><object><name>window</name><pose>Unspecified</pose><truncated>0</truncated><difficult>0</difficult><bndbox><x_center>1912</x_center><y_center>388</y_center><phi>3.1137764686361336</phi><theta>0.30270554214276657</theta><w>20</w><h>28</h></bndbox></object><object><name>window</name><pose>Unspecified</pose><truncated>0</truncated><difficult>0</difficult><bndbox><x_center>1657</x_center><y_center>398</y_center><phi>2.279290920026345</phi><theta>0.2699806186678728</theta><w>20</w><h>52</h></bndbox></object><object><name>door</name><pose>Unspecified</pose><truncated>0</truncated><difficult>0</difficult><bndbox><x_center>256</x_center><y_center>491</y_center><phi>-2.3054708588062596</phi><theta>-0.0343611696486385</theta><w>8</w><h>12</h></bndbox></object></annotation>