<annotation><folder>VOC2012</folder><filename>40133492504_eee064a01a_o.jpg</filename><source><database>The VOC2007 Database</database><annotation>PASCAL VOC2007</annotation><image>flickr</image></source><size><width>1920</width><height>960</height><depth>3</depth></size><segmented>0</segmented><object><name>book</name><pose>Unspecified</pose><truncated>0</truncated><difficult>0</difficult><bndbox><x_center>829</x_center><y_center>577</y_center><phi>-0.4303327436948518</phi><theta>-0.31579551153272384</theta><w>4</w><h>4</h></bndbox></object><object><name>phone</name><pose>Unspecified</pose><truncated>0</truncated><difficult>0</difficult><bndbox><x_center>0</x_center><y_center>671</y_center><phi>-3.1432288997635376</phi><theta>-0.6234097921967248</theta><w>8</w><h>4</h></bndbox></object><object><name>tv</name><pose>Unspecified</pose><truncated>0</truncated><difficult>0</difficult><bndbox><x_center>446</x_center><y_center>517</y_center><phi>-1.6836973127832795</phi><theta>-0.11944597068336177</theta><w>32</w><h>20</h></bndbox></object><object><name>light</name><pose>Unspecified</pose><truncated>0</truncated><difficult>0</difficult><bndbox><x_center>1354</x_center><y_center>133</y_center><phi>1.2877257387370662</phi><theta>1.1371910907525553</theta><w>32</w><h>32</h></bndbox></object><object><name>sofa</name><pose>Unspecified</pose><truncated>0</truncated><difficult>0</difficult><bndbox><x_center>1396</x_center><y_center>698</y_center><phi>1.4251704173316195</phi><theta>-0.7117670855789375</theta><w>68</w><h>40</h></bndbox></object><object><name>sofa</name><pose>Unspecified</pose><truncated>0</truncated><difficult>0</difficult><bndbox><x_center>809</x_center><y_center>680</y_center><phi>-0.4957825906446393</phi><theta>-0.6528622233241287</theta><w>28</w><h>32</h></bndbox></object><object><name>computer</name><pose>Unspecified</pose><truncated>0</truncated><difficult>0</difficult><bndbox><x_center>2</x_center><y_center>703</y_center><phi>-3.136683915068559</phi><theta>-0.7281295473163845</theta><w>12</w><h>8</h></bndbox></object><object><name>cup</name><pose>Unspecified</pose><truncated>0</truncated><difficult>0</difficult><bndbox><x_center>60</x_center><y_center>670</y_center><phi>-2.9468793589141757</phi><theta>-0.6201372998492352</theta><w>4</w><h>8</h></bndbox></object><object><name>chair</name><pose>Unspecified</pose><truncated>0</truncated><difficult>0</difficult><bndbox><x_center>802</x_center><y_center>677</y_center><phi>-0.518690037077065</phi><theta>-0.6430447462816609</theta><w>32</w><h>32</h></bndbox></object><object><name>chair</name><pose>Unspecified</pose><truncated>0</truncated><difficult>0</difficult><bndbox><x_center>170</x_center><y_center>802</y_center><phi>-2.5869052006903455</phi><theta>-1.0521062897178315</theta><w>24</w><h>28</h></bndbox></object><object><name>chair</name><pose>Unspecified</pose><truncated>0</truncated><difficult>0</difficult><bndbox><x_center>254</x_center><y_center>655</y_center><phi>-2.3120158435012383</phi><theta>-0.5710499146368947</theta><w>12</w><h>16</h></bndbox></object><object><name>chair</name><pose>Unspecified</pose><truncated>0</truncated><difficult>0</difficult><bndbox><x_center>1762</x_center><y_center>709</y_center><phi>2.6229026165127287</phi><theta>-0.7477645014013206</theta><w>16</w><h>40</h></bndbox></object><object><name>chair</name><pose>Unspecified</pose><truncated>0</truncated><difficult>0</difficult><bndbox><x_center>62</x_center><y_center>638</y_center><phi>-2.940334374219197</phi><theta>-0.5154175447295755</theta><w>16</w><h>12</h></bndbox></object><object><name>window</name><pose>Unspecified</pose><truncated>0</truncated><difficult>0</difficult><bndbox><x_center>163</x_center><y_center>494</y_center><phi>-2.6098126471227707</phi><theta>-0.044178646691106396</theta><w>44</w><h>60</h></bndbox></object><object><name>window</name><pose>Unspecified</pose><truncated>0</truncated><difficult>0</difficult><bndbox><x_center>1685</x_center><y_center>479</y_center><phi>2.370920705756047</phi><theta>0.004908738521234121</theta><w>28</w><h>48</h></bndbox></object><object><name>window</name><pose>Unspecified</pose><truncated>0</truncated><difficult>0</difficult><bndbox><x_center>838</x_center><y_center>481</y_center><phi>-0.40088031256744744</phi><theta>-0.0016362461737445908</theta><w>8</w><h>20</h></bndbox></object><object><name>door</name><pose>Unspecified</pose><truncated>0</truncated><difficult>0</difficult><bndbox><x_center>937</x_center><y_center>516</y_center><phi>-0.0769035701660003</phi><theta>-0.11617347833587258</theta><w>12</w><h>40</h></bndbox></object><object><name>door</name><pose>Unspecified</pose><truncated>0</truncated><difficult>0</difficult><bndbox><x_center>1055</x_center><y_center>522</y_center><phi>0.3092505268377451</phi><theta>-0.13580843242080873</theta><w>16</w><h>40</h></bndbox></object><object><name>door</name><pose>Unspecified</pose><truncated>0</truncated><difficult>0</difficult><bndbox><x_center>715</x_center><y_center>515</y_center><phi>-0.8033968713086398</phi><theta>-0.11290098598838305</theta><w>4</w><h>32</h></bndbox></object><object><name>heater</name><pose>Unspecified</pose><truncated>0</truncated><difficult>0</difficult><bndbox><x_center>671</x_center><y_center>609</y_center><phi>-0.9473865345981718</phi><theta>-0.4205152666523839</theta><w>8</w><h>20</h></bndbox></object><object><name>fireplace</name><pose>Unspecified</pose><truncated>0</truncated><difficult>0</difficult><bndbox><x_center>455</x_center><y_center>637</y_center><phi>-1.6542448816558757</phi><theta>-0.5121450523820859</theta><w>32</w><h>28</h></bndbox></object><object><name>vase</name><pose>Unspecified</pose><truncated>0</truncated><difficult>0</difficult><bndbox><x_center>119</x_center><y_center>687</y_center><phi>-2.7538023104123033</phi><theta>-0.6757696697565544</theta><w>8</w><h>8</h></bndbox></object><object><name>table</name><pose>Unspecified</pose><truncated>0</truncated><difficult>0</difficult><bndbox><x_center>119</x_center><y_center>758</y_center><phi>-2.7538023104123033</phi><theta>-0.9081166264282996</theta><w>56</w><h>40</h></bndbox></object><object><name>table</name><pose>Unspecified</pose><truncated>0</truncated><difficult>0</difficult><bndbox><x_center>1179</x_center><y_center>750</y_center><phi>0.7150395779264267</phi><theta>-0.8819366876483847</theta><w>32</w><h>32</h></bndbox></object></annotation>