<annotation><folder>VOC2012</folder><filename>4778568133_6ea7b5f0fe_o.jpg</filename><source><database>The VOC2007 Database</database><annotation>PASCAL VOC2007</annotation><image>flickr</image></source><size><width>1920</width><height>960</height><depth>3</depth></size><segmented>0</segmented><object><name>light</name><pose>Unspecified</pose><truncated>0</truncated><difficult>0</difficult><bndbox><x_center>523</x_center><y_center>299</y_center><phi>-1.4317154020265983</phi><theta>0.5939573610693203</theta><w>8</w><h>8</h></bndbox></object><object><name>light</name><pose>Unspecified</pose><truncated>0</truncated><difficult>0</difficult><bndbox><x_center>445</x_center><y_center>298</y_center><phi>-1.686969805130769</phi><theta>0.5972298534168097</theta><w>8</w><h>20</h></bndbox></object><object><name>window</name><pose>Unspecified</pose><truncated>0</truncated><difficult>0</difficult><bndbox><x_center>491</x_center><y_center>218</y_center><phi>-1.536435157146258</phi><theta>0.859029241215959</theta><w>36</w><h>16</h></bndbox></object><object><name>window</name><pose>Unspecified</pose><truncated>0</truncated><difficult>0</difficult><bndbox><x_center>814</x_center><y_center>323</y_center><phi>-0.4794201289071923</phi><theta>0.5154175447295755</theta><w>16</w><h>12</h></bndbox></object><object><name>window</name><pose>Unspecified</pose><truncated>0</truncated><difficult>0</difficult><bndbox><x_center>167</x_center><y_center>317</y_center><phi>-2.596722677732813</phi><theta>0.5350524988145116</theta><w>16</w><h>12</h></bndbox></object><object><name>door</name><pose>Unspecified</pose><truncated>0</truncated><difficult>0</difficult><bndbox><x_center>484</x_center><y_center>418</y_center><phi>-1.5593426035786837</phi><theta>0.20453077171808554</theta><w>52</w><h>100</h></bndbox></object></annotation>