<annotation><folder>VOC2012</folder><filename>7l1wj.jpg</filename><source><database>The VOC2007 Database</database><annotation>PASCAL VOC2007</annotation><image>flickr</image></source><size><width>1920</width><height>960</height><depth>3</depth></size><segmented>0</segmented><object><name>keyboard</name><pose>Unspecified</pose><truncated>0</truncated><difficult>0</difficult><bndbox><x_center>290</x_center><y_center>586</y_center><phi>-2.1942061189916213</phi><theta>-0.3452479426601282</theta><w>8</w><h>4</h></bndbox></object><object><name>keyboard</name><pose>Unspecified</pose><truncated>0</truncated><difficult>0</difficult><bndbox><x_center>370</x_center><y_center>548</y_center><phi>-1.9324067311924717</phi><theta>-0.22089323345553233</theta><w>4</w><h>4</h></bndbox></object><object><name>keyboard</name><pose>Unspecified</pose><truncated>0</truncated><difficult>0</difficult><bndbox><x_center>487</x_center><y_center>518</y_center><phi>-1.5495251265362158</phi><theta>-0.1227184630308513</theta><w>4</w><h>4</h></bndbox></object><object><name>keyboard</name><pose>Unspecified</pose><truncated>0</truncated><difficult>0</difficult><bndbox><x_center>620</x_center><y_center>542</y_center><phi>-1.1142836443201298</phi><theta>-0.2012582793705962</theta><w>4</w><h>4</h></bndbox></object><object><name>keyboard</name><pose>Unspecified</pose><truncated>0</truncated><difficult>0</difficult><bndbox><x_center>713</x_center><y_center>575</y_center><phi>-0.8099418560036186</phi><theta>-0.3092505268377451</theta><w>8</w><h>4</h></bndbox></object><object><name>keyboard</name><pose>Unspecified</pose><truncated>0</truncated><difficult>0</difficult><bndbox><x_center>1668</x_center><y_center>616</y_center><phi>2.315288335848728</phi><theta>-0.44342271308480924</theta><w>8</w><h>4</h></bndbox></object><object><name>keyboard</name><pose>Unspecified</pose><truncated>0</truncated><difficult>0</difficult><bndbox><x_center>1259</x_center><y_center>634</y_center><phi>0.9768389657255766</phi><theta>-0.502327575339618</theta><w>8</w><h>8</h></bndbox></object><object><name>light</name><pose>Unspecified</pose><truncated>0</truncated><difficult>0</difficult><bndbox><x_center>1090</x_center><y_center>408</y_center><phi>0.4237877589998735</phi><theta>0.23725569519297912</theta><w>24</w><h>8</h></bndbox></object><object><name>light</name><pose>Unspecified</pose><truncated>0</truncated><difficult>0</difficult><bndbox><x_center>1212</x_center><y_center>426</y_center><phi>0.823031825393576</phi><theta>0.17835083293817053</theta><w>16</w><h>8</h></bndbox></object><object><name>light</name><pose>Unspecified</pose><truncated>0</truncated><difficult>0</difficult><bndbox><x_center>1346</x_center><y_center>413</y_center><phi>1.2615457999571515</phi><theta>0.22089323345553233</theta><w>12</w><h>8</h></bndbox></object><object><name>light</name><pose>Unspecified</pose><truncated>0</truncated><difficult>0</difficult><bndbox><x_center>1234</x_center><y_center>345</y_center><phi>0.8950266570383422</phi><theta>0.4434227130848094</theta><w>24</w><h>16</h></bndbox></object><object><name>light</name><pose>Unspecified</pose><truncated>0</truncated><difficult>0</difficult><bndbox><x_center>1521</x_center><y_center>414</y_center><phi>1.8342319607677904</phi><theta>0.21762074110804297</theta><w>12</w><h>8</h></bndbox></object><object><name>light</name><pose>Unspecified</pose><truncated>0</truncated><difficult>0</difficult><bndbox><x_center>1623</x_center><y_center>346</y_center><phi>2.1680261802117062</phi><theta>0.4401502207373199</theta><w>24</w><h>16</h></bndbox></object><object><name>computer</name><pose>Unspecified</pose><truncated>0</truncated><difficult>0</difficult><bndbox><x_center>717</x_center><y_center>559</y_center><phi>-0.7968518866136611</phi><theta>-0.25689064927791544</theta><w>8</w><h>8</h></bndbox></object><object><name>computer</name><pose>Unspecified</pose><truncated>0</truncated><difficult>0</difficult><bndbox><x_center>618</x_center><y_center>530</y_center><phi>-1.1208286290151086</phi><theta>-0.16198837120072357</theta><w>4</w><h>4</h></bndbox></object><object><name>computer</name><pose>Unspecified</pose><truncated>0</truncated><difficult>0</difficult><bndbox><x_center>290</x_center><y_center>580</y_center><phi>-2.1942061189916213</phi><theta>-0.32561298857519205</theta><w>12</w><h>8</h></bndbox></object><object><name>computer</name><pose>Unspecified</pose><truncated>0</truncated><difficult>0</difficult><bndbox><x_center>359</x_center><y_center>535</y_center><phi>-1.9684041470148548</phi><theta>-0.17835083293817053</theta><w>8</w><h>8</h></bndbox></object><object><name>computer</name><pose>Unspecified</pose><truncated>0</truncated><difficult>0</difficult><bndbox><x_center>1272</x_center><y_center>634</y_center><phi>1.019381366242938</phi><theta>-0.502327575339618</theta><w>16</w><h>16</h></bndbox></object><object><name>computer</name><pose>Unspecified</pose><truncated>0</truncated><difficult>0</difficult><bndbox><x_center>1669</x_center><y_center>603</y_center><phi>2.318560828196217</phi><theta>-0.40088031256744744</theta><w>16</w><h>16</h></bndbox></object><object><name>computer</name><pose>Unspecified</pose><truncated>0</truncated><difficult>0</difficult><bndbox><x_center>1098</x_center><y_center>554</y_center><phi>0.4499676977797883</phi><theta>-0.24052818754046845</theta><w>8</w><h>8</h></bndbox></object><object><name>computer</name><pose>Unspecified</pose><truncated>0</truncated><difficult>0</difficult><bndbox><x_center>1249</x_center><y_center>528</y_center><phi>0.9441140422506826</phi><theta>-0.15544338650574485</theta><w>4</w><h>4</h></bndbox></object><object><name>computer</name><pose>Unspecified</pose><truncated>0</truncated><difficult>0</difficult><bndbox><x_center>1163</x_center><y_center>518</y_center><phi>0.662679700366597</phi><theta>-0.1227184630308513</theta><w>4</w><h>4</h></bndbox></object><object><name>computer</name><pose>Unspecified</pose><truncated>0</truncated><difficult>0</difficult><bndbox><x_center>1076</x_center><y_center>520</y_center><phi>0.3779728661350221</phi><theta>-0.12926344772583</theta><w>4</w><h>4</h></bndbox></object><object><name>computer</name><pose>Unspecified</pose><truncated>0</truncated><difficult>0</difficult><bndbox><x_center>897</x_center><y_center>526</y_center><phi>-0.2078032640655749</phi><theta>-0.14889840181076613</theta><w>4</w><h>4</h></bndbox></object><object><name>computer</name><pose>Unspecified</pose><truncated>0</truncated><difficult>0</difficult><bndbox><x_center>397</x_center><y_center>510</y_center><phi>-1.8440494378102585</phi><theta>-0.09653852425093644</theta><w>4</w><h>4</h></bndbox></object><object><name>computer</name><pose>Unspecified</pose><truncated>0</truncated><difficult>0</difficult><bndbox><x_center>484</x_center><y_center>511</y_center><phi>-1.5593426035786837</phi><theta>-0.09981101659842563</theta><w>4</w><h>4</h></bndbox></object><object><name>chair</name><pose>Unspecified</pose><truncated>0</truncated><difficult>0</difficult><bndbox><x_center>641</x_center><y_center>629</y_center><phi>-1.045561305022853</phi><theta>-0.48596511360217104</theta><w>16</w><h>24</h></bndbox></object><object><name>chair</name><pose>Unspecified</pose><truncated>0</truncated><difficult>0</difficult><bndbox><x_center>1555</x_center><y_center>685</y_center><phi>1.9454967005824295</phi><theta>-0.6692246850615757</theta><w>24</w><h>36</h></bndbox></object><object><name>chair</name><pose>Unspecified</pose><truncated>0</truncated><difficult>0</difficult><bndbox><x_center>377</x_center><y_center>649</y_center><phi>-1.909499284760046</phi><theta>-0.5514149605519585</theta><w>16</w><h>28</h></bndbox></object><object><name>chair</name><pose>Unspecified</pose><truncated>0</truncated><difficult>0</difficult><bndbox><x_center>940</x_center><y_center>550</y_center><phi>-0.06708609312353206</phi><theta>-0.22743821815051105</theta><w>8</w><h>16</h></bndbox></object><object><name>chair</name><pose>Unspecified</pose><truncated>0</truncated><difficult>0</difficult><bndbox><x_center>1174</x_center><y_center>632</y_center><phi>0.6986771161889801</phi><theta>-0.4957825906446393</theta><w>16</w><h>28</h></bndbox></object><object><name>chair</name><pose>Unspecified</pose><truncated>0</truncated><difficult>0</difficult><bndbox><x_center>1312</x_center><y_center>543</y_center><phi>1.150281060142513</phi><theta>-0.20453077171808537</theta><w>8</w><h>8</h></bndbox></object><object><name>chair</name><pose>Unspecified</pose><truncated>0</truncated><difficult>0</difficult><bndbox><x_center>1028</x_center><y_center>542</y_center><phi>0.22089323345553233</phi><theta>-0.2012582793705962</theta><w>8</w><h>12</h></bndbox></object><object><name>chair</name><pose>Unspecified</pose><truncated>0</truncated><difficult>0</difficult><bndbox><x_center>572</x_center><y_center>570</y_center><phi>-1.2713632769996193</phi><theta>-0.2928880651002985</theta><w>12</w><h>16</h></bndbox></object><object><name>chair</name><pose>Unspecified</pose><truncated>0</truncated><difficult>0</difficult><bndbox><x_center>424</x_center><y_center>570</y_center><phi>-1.7556921444280458</phi><theta>-0.2928880651002985</theta><w>8</w><h>16</h></bndbox></object><object><name>chair</name><pose>Unspecified</pose><truncated>0</truncated><difficult>0</difficult><bndbox><x_center>514</x_center><y_center>528</y_center><phi>-1.4611678331540028</phi><theta>-0.15544338650574485</theta><w>8</w><h>8</h></bndbox></object><object><name>window</name><pose>Unspecified</pose><truncated>0</truncated><difficult>0</difficult><bndbox><x_center>1357</x_center><y_center>500</y_center><phi>1.2975432157795346</phi><theta>-0.06381360077604253</theta><w>56</w><h>24</h></bndbox></object><object><name>window</name><pose>Unspecified</pose><truncated>0</truncated><difficult>0</difficult><bndbox><x_center>1097</x_center><y_center>497</y_center><phi>0.4466952054322984</phi><theta>-0.05399612373357464</theta><w>32</w><h>24</h></bndbox></object><object><name>window</name><pose>Unspecified</pose><truncated>0</truncated><difficult>0</difficult><bndbox><x_center>922</x_center><y_center>502</y_center><phi>-0.12599095537834082</phi><theta>-0.07035858547102125</theta><w>24</w><h>28</h></bndbox></object><object><name>table</name><pose>Unspecified</pose><truncated>0</truncated><difficult>0</difficult><bndbox><x_center>285</x_center><y_center>643</y_center><phi>-2.210568580729068</phi><theta>-0.5317800064670224</theta><w>52</w><h>40</h></bndbox></object><object><name>table</name><pose>Unspecified</pose><truncated>0</truncated><difficult>0</difficult><bndbox><x_center>715</x_center><y_center>631</y_center><phi>-0.8033968713086398</phi><theta>-0.49251009829714976</theta><w>52</w><h>32</h></bndbox></object><object><name>table</name><pose>Unspecified</pose><truncated>0</truncated><difficult>0</difficult><bndbox><x_center>1625</x_center><y_center>669</y_center><phi>2.1745711649066846</phi><theta>-0.616864807501746</theta><w>68</w><h>36</h></bndbox></object><object><name>table</name><pose>Unspecified</pose><truncated>0</truncated><difficult>0</difficult><bndbox><x_center>1209</x_center><y_center>682</y_center><phi>0.8132143483511077</phi><theta>-0.6594072080191075</theta><w>68</w><h>56</h></bndbox></object><object><name>table</name><pose>Unspecified</pose><truncated>0</truncated><difficult>0</difficult><bndbox><x_center>896</x_center><y_center>563</y_center><phi>-0.2110757564130641</phi><theta>-0.2699806186678728</theta><w>8</w><h>12</h></bndbox></object><object><name>table</name><pose>Unspecified</pose><truncated>0</truncated><difficult>0</difficult><bndbox><x_center>505</x_center><y_center>618</y_center><phi>-1.490620264281407</phi><theta>-0.44996769777978796</theta><w>20</w><h>20</h></bndbox></object><object><name>table</name><pose>Unspecified</pose><truncated>0</truncated><difficult>0</difficult><bndbox><x_center>450</x_center><y_center>535</y_center><phi>-1.6706073433933222</phi><theta>-0.17835083293817053</theta><w>32</w><h>8</h></bndbox></object></annotation>