<annotation><folder>VOC2012</folder><filename>7l3ch.jpg</filename><source><database>The VOC2007 Database</database><annotation>PASCAL VOC2007</annotation><image>flickr</image></source><size><width>1920</width><height>960</height><depth>3</depth></size><segmented>0</segmented><object><name>mirror</name><pose>Unspecified</pose><truncated>0</truncated><difficult>0</difficult><bndbox><x_center>1336</x_center><y_center>511</y_center><phi>1.2288208764822575</phi><theta>-0.09981101659842563</theta><w>48</w><h>56</h></bndbox></object><object><name>light</name><pose>Unspecified</pose><truncated>0</truncated><difficult>0</difficult><bndbox><x_center>182</x_center><y_center>134</y_center><phi>-2.547635292520473</phi><theta>1.133918598405066</theta><w>16</w><h>20</h></bndbox></object><object><name>bathtub</name><pose>Unspecified</pose><truncated>0</truncated><difficult>0</difficult><bndbox><x_center>908</x_center><y_center>721</y_center><phi>-0.1718058482431918</phi><theta>-0.7870344095711929</theta><w>64</w><h>28</h></bndbox></object><object><name>sink</name><pose>Unspecified</pose><truncated>0</truncated><difficult>0</difficult><bndbox><x_center>1258</x_center><y_center>763</y_center><phi>0.9735664733780867</phi><theta>-0.9244790881657465</theta><w>44</w><h>36</h></bndbox></object><object><name>washer</name><pose>Unspecified</pose><truncated>0</truncated><difficult>0</difficult><bndbox><x_center>1600</x_center><y_center>802</y_center><phi>2.0927588562194512</phi><theta>-1.0521062897178315</theta><w>40</w><h>48</h></bndbox></object><object><name>window</name><pose>Unspecified</pose><truncated>0</truncated><difficult>0</difficult><bndbox><x_center>908</x_center><y_center>386</y_center><phi>-0.1718058482431918</phi><theta>0.3092505268377453</theta><w>44</w><h>20</h></bndbox></object><object><name>door</name><pose>Unspecified</pose><truncated>0</truncated><difficult>0</difficult><bndbox><x_center>327</x_center><y_center>596</y_center><phi>-2.0731239021345145</phi><theta>-0.3779728661350221</theta><w>52</w><h>104</h></bndbox></object><object><name>heater</name><pose>Unspecified</pose><truncated>0</truncated><difficult>0</difficult><bndbox><x_center>578</x_center><y_center>580</y_center><phi>-1.2517283229146832</phi><theta>-0.32561298857519205</theta><w>32</w><h>84</h></bndbox></object><object><name>heater</name><pose>Unspecified</pose><truncated>0</truncated><difficult>0</difficult><bndbox><x_center>578</x_center><y_center>580</y_center><phi>-1.2517283229146832</phi><theta>-0.32561298857519205</theta><w>32</w><h>84</h></bndbox></object></annotation>