<annotation><folder>VOC2012</folder><filename>7l6TY.jpg</filename><source><database>The VOC2007 Database</database><annotation>PASCAL VOC2007</annotation><image>flickr</image></source><size><width>1920</width><height>960</height><depth>3</depth></size><segmented>0</segmented><object><name>mirror</name><pose>Unspecified</pose><truncated>0</truncated><difficult>0</difficult><bndbox><x_center>973</x_center><y_center>313</y_center><phi>0.040906154343616864</phi><theta>0.5481424682044692</theta><w>80</w><h>60</h></bndbox></object><object><name>mirror</name><pose>Unspecified</pose><truncated>0</truncated><difficult>0</difficult><bndbox><x_center>1309</x_center><y_center>248</y_center><phi>1.1404635831000447</phi><theta>0.760854470791278</theta><w>32</w><h>40</h></bndbox></object><object><name>light</name><pose>Unspecified</pose><truncated>0</truncated><difficult>0</difficult><bndbox><x_center>959</x_center><y_center>127</y_center><phi>-0.004908738521234121</phi><theta>1.1568260448374914</theta><w>32</w><h>12</h></bndbox></object><object><name>sink</name><pose>Unspecified</pose><truncated>0</truncated><difficult>0</difficult><bndbox><x_center>959</x_center><y_center>707</y_center><phi>-0.004908738521234121</phi><theta>-0.7412195167063419</theta><w>96</w><h>84</h></bndbox></object><object><name>cup</name><pose>Unspecified</pose><truncated>0</truncated><difficult>0</difficult><bndbox><x_center>1199</x_center><y_center>523</y_center><phi>0.7804894248762145</phi><theta>-0.13908092476829825</theta><w>12</w><h>12</h></bndbox></object><object><name>bottle</name><pose>Unspecified</pose><truncated>0</truncated><difficult>0</difficult><bndbox><x_center>1120</x_center><y_center>509</y_center><phi>0.5219625294245545</phi><theta>-0.09326603190344691</theta><w>8</w><h>20</h></bndbox></object><object><name>bottle</name><pose>Unspecified</pose><truncated>0</truncated><difficult>0</difficult><bndbox><x_center>681</x_center><y_center>522</y_center><phi>-0.9146616111232783</phi><theta>-0.13580843242080873</theta><w>8</w><h>20</h></bndbox></object><object><name>bottle</name><pose>Unspecified</pose><truncated>0</truncated><difficult>0</difficult><bndbox><x_center>782</x_center><y_center>505</y_center><phi>-0.5841398840268521</phi><theta>-0.0801760625134895</theta><w>16</w><h>36</h></bndbox></object><object><name>door</name><pose>Unspecified</pose><truncated>0</truncated><difficult>0</difficult><bndbox><x_center>1867</x_center><y_center>487</y_center><phi>2.966514312999112</phi><theta>-0.021271200258680727</theta><w>44</w><h>116</h></bndbox></object></annotation>