<annotation><folder>VOC2012</folder><filename>7lX6G.jpg</filename><source><database>The VOC2007 Database</database><annotation>PASCAL VOC2007</annotation><image>flickr</image></source><size><width>1920</width><height>960</height><depth>3</depth></size><segmented>0</segmented><object><name>board</name><pose>Unspecified</pose><truncated>0</truncated><difficult>0</difficult><bndbox><x_center>806</x_center><y_center>503</y_center><phi>-0.5056000676871072</phi><theta>-0.07363107781851078</theta><w>40</w><h>28</h></bndbox></object><object><name>potted plant</name><pose>Unspecified</pose><truncated>0</truncated><difficult>0</difficult><bndbox><x_center>1703</x_center><y_center>500</y_center><phi>2.429825568010856</phi><theta>-0.06381360077604253</theta><w>12</w><h>8</h></bndbox></object><object><name>book</name><pose>Unspecified</pose><truncated>0</truncated><difficult>0</difficult><bndbox><x_center>385</x_center><y_center>692</y_center><phi>-1.8833193459801312</phi><theta>-0.6921321314940013</theta><w>16</w><h>24</h></bndbox></object><object><name>book</name><pose>Unspecified</pose><truncated>0</truncated><difficult>0</difficult><bndbox><x_center>460</x_center><y_center>617</y_center><phi>-1.6378824199184285</phi><theta>-0.4466952054322988</theta><w>16</w><h>12</h></bndbox></object><object><name>book</name><pose>Unspecified</pose><truncated>0</truncated><difficult>0</difficult><bndbox><x_center>587</x_center><y_center>440</y_center><phi>-1.222275891787279</phi><theta>0.13253594007331937</theta><w>24</w><h>12</h></bndbox></object><object><name>book</name><pose>Unspecified</pose><truncated>0</truncated><difficult>0</difficult><bndbox><x_center>579</x_center><y_center>534</y_center><phi>-1.2484558305671936</phi><theta>-0.17507834059068134</theta><w>16</w><h>12</h></bndbox></object><object><name>book</name><pose>Unspecified</pose><truncated>0</truncated><difficult>0</difficult><bndbox><x_center>587</x_center><y_center>592</y_center><phi>-1.222275891787279</phi><theta>-0.36488289674506436</theta><w>20</w><h>12</h></bndbox></object><object><name>book</name><pose>Unspecified</pose><truncated>0</truncated><difficult>0</difficult><bndbox><x_center>594</x_center><y_center>653</y_center><phi>-1.1993684453548532</phi><theta>-0.5645049299419159</theta><w>20</w><h>12</h></bndbox></object><object><name>book</name><pose>Unspecified</pose><truncated>0</truncated><difficult>0</difficult><bndbox><x_center>607</x_center><y_center>696</y_center><phi>-1.1568260448374916</phi><theta>-0.7052221008839588</theta><w>16</w><h>12</h></bndbox></object><object><name>book</name><pose>Unspecified</pose><truncated>0</truncated><difficult>0</difficult><bndbox><x_center>992</x_center><y_center>516</y_center><phi>0.10308350894591481</phi><theta>-0.11617347833587258</theta><w>8</w><h>4</h></bndbox></object><object><name>book</name><pose>Unspecified</pose><truncated>0</truncated><difficult>0</difficult><bndbox><x_center>995</x_center><y_center>547</y_center><phi>0.11290098598838305</phi><theta>-0.2176207411080428</theta><w>8</w><h>4</h></bndbox></object><object><name>book</name><pose>Unspecified</pose><truncated>0</truncated><difficult>0</difficult><bndbox><x_center>997</x_center><y_center>582</y_center><phi>0.11944597068336212</phi><theta>-0.33215797327017077</theta><w>8</w><h>4</h></bndbox></object><object><name>book</name><pose>Unspecified</pose><truncated>0</truncated><difficult>0</difficult><bndbox><x_center>1074</x_center><y_center>447</y_center><phi>0.3714278814400431</phi><theta>0.10962849364089387</theta><w>8</w><h>4</h></bndbox></object><object><name>book</name><pose>Unspecified</pose><truncated>0</truncated><difficult>0</difficult><bndbox><x_center>1076</x_center><y_center>480</y_center><phi>0.3779728661350221</phi><theta>0.0016362461737447654</theta><w>8</w><h>4</h></bndbox></object><object><name>book</name><pose>Unspecified</pose><truncated>0</truncated><difficult>0</difficult><bndbox><x_center>1076</x_center><y_center>510</y_center><phi>0.3779728661350221</phi><theta>-0.09653852425093644</theta><w>8</w><h>4</h></bndbox></object><object><name>book</name><pose>Unspecified</pose><truncated>0</truncated><difficult>0</difficult><bndbox><x_center>1076</x_center><y_center>534</y_center><phi>0.3779728661350221</phi><theta>-0.17507834059068134</theta><w>8</w><h>4</h></bndbox></object><object><name>book</name><pose>Unspecified</pose><truncated>0</truncated><difficult>0</difficult><bndbox><x_center>1076</x_center><y_center>566</y_center><phi>0.3779728661350221</phi><theta>-0.2797980957103411</theta><w>8</w><h>4</h></bndbox></object><object><name>book</name><pose>Unspecified</pose><truncated>0</truncated><difficult>0</difficult><bndbox><x_center>849</x_center><y_center>609</y_center><phi>-0.36488289674506436</phi><theta>-0.4205152666523839</theta><w>20</w><h>4</h></bndbox></object><object><name>book</name><pose>Unspecified</pose><truncated>0</truncated><difficult>0</difficult><bndbox><x_center>1139</x_center><y_center>513</y_center><phi>0.5841398840268525</phi><theta>-0.10635600129340433</theta><w>16</w><h>12</h></bndbox></object><object><name>book</name><pose>Unspecified</pose><truncated>0</truncated><difficult>0</difficult><bndbox><x_center>1206</x_center><y_center>486</y_center><phi>0.8033968713086395</phi><theta>-0.017998707911191545</theta><w>8</w><h>12</h></bndbox></object><object><name>book</name><pose>Unspecified</pose><truncated>0</truncated><difficult>0</difficult><bndbox><x_center>1592</x_center><y_center>502</y_center><phi>2.0665789174395357</phi><theta>-0.07035858547102125</theta><w>8</w><h>4</h></bndbox></object><object><name>book</name><pose>Unspecified</pose><truncated>0</truncated><difficult>0</difficult><bndbox><x_center>1633</x_center><y_center>503</y_center><phi>2.2007511036865997</phi><theta>-0.07363107781851078</theta><w>8</w><h>4</h></bndbox></object><object><name>book</name><pose>Unspecified</pose><truncated>0</truncated><difficult>0</difficult><bndbox><x_center>1636</x_center><y_center>484</y_center><phi>2.210568580729068</phi><theta>-0.011453723216212833</theta><w>8</w><h>4</h></bndbox></object><object><name>book</name><pose>Unspecified</pose><truncated>0</truncated><difficult>0</difficult><bndbox><x_center>1594</x_center><y_center>483</y_center><phi>2.0731239021345145</phi><theta>-0.008181230868723303</theta><w>8</w><h>4</h></bndbox></object><object><name>book</name><pose>Unspecified</pose><truncated>0</truncated><difficult>0</difficult><bndbox><x_center>1587</x_center><y_center>522</y_center><phi>2.0502164557020888</phi><theta>-0.13580843242080873</theta><w>8</w><h>4</h></bndbox></object><object><name>book</name><pose>Unspecified</pose><truncated>0</truncated><difficult>0</difficult><bndbox><x_center>1637</x_center><y_center>527</y_center><phi>2.213841073076557</phi><theta>-0.1521708941582557</theta><w>8</w><h>4</h></bndbox></object><object><name>book</name><pose>Unspecified</pose><truncated>0</truncated><difficult>0</difficult><bndbox><x_center>1472</x_center><y_center>508</y_center><phi>1.6738798357408113</phi><theta>-0.08999353955595774</theta><w>16</w><h>8</h></bndbox></object><object><name>cabinet</name><pose>Unspecified</pose><truncated>0</truncated><difficult>0</difficult><bndbox><x_center>592</x_center><y_center>539</y_center><phi>-1.2059134300498322</phi><theta>-0.19144080232812793</theta><w>40</w><h>80</h></bndbox></object><object><name>cabinet</name><pose>Unspecified</pose><truncated>0</truncated><difficult>0</difficult><bndbox><x_center>975</x_center><y_center>552</y_center><phi>0.04745113903859593</phi><theta>-0.23398320284548976</theta><w>20</w><h>24</h></bndbox></object><object><name>cabinet</name><pose>Unspecified</pose><truncated>0</truncated><difficult>0</difficult><bndbox><x_center>1064</x_center><y_center>508</y_center><phi>0.3387029579651499</phi><theta>-0.08999353955595774</theta><w>12</w><h>32</h></bndbox></object><object><name>cabinet</name><pose>Unspecified</pose><truncated>0</truncated><difficult>0</difficult><bndbox><x_center>1134</x_center><y_center>511</y_center><phi>0.5677774222894051</phi><theta>-0.09981101659842563</theta><w>16</w><h>12</h></bndbox></object><object><name>cabinet</name><pose>Unspecified</pose><truncated>0</truncated><difficult>0</difficult><bndbox><x_center>1206</x_center><y_center>478</y_center><phi>0.8033968713086395</phi><theta>0.008181230868723478</theta><w>8</w><h>8</h></bndbox></object><object><name>cabinet</name><pose>Unspecified</pose><truncated>0</truncated><difficult>0</difficult><bndbox><x_center>1326</x_center><y_center>498</y_center><phi>1.1960959530073636</phi><theta>-0.057268616081063824</theta><w>12</w><h>8</h></bndbox></object><object><name>cabinet</name><pose>Unspecified</pose><truncated>0</truncated><difficult>0</difficult><bndbox><x_center>1469</x_center><y_center>500</y_center><phi>1.6640623586983438</phi><theta>-0.06381360077604253</theta><w>16</w><h>8</h></bndbox></object><object><name>cabinet</name><pose>Unspecified</pose><truncated>0</truncated><difficult>0</difficult><bndbox><x_center>1603</x_center><y_center>515</y_center><phi>2.1025763332619185</phi><theta>-0.11290098598838305</theta><w>20</w><h>12</h></bndbox></object><object><name>sofa</name><pose>Unspecified</pose><truncated>0</truncated><difficult>0</difficult><bndbox><x_center>815</x_center><y_center>734</y_center><phi>-0.47614763655970316</phi><theta>-0.8295768100885547</theta><w>56</w><h>60</h></bndbox></object><object><name>computer</name><pose>Unspecified</pose><truncated>0</truncated><difficult>0</difficult><bndbox><x_center>812</x_center><y_center>850</y_center><phi>-0.48596511360217104</phi><theta>-1.2091859223973214</theta><w>20</w><h>16</h></bndbox></object><object><name>chair</name><pose>Unspecified</pose><truncated>0</truncated><difficult>0</difficult><bndbox><x_center>955</x_center><y_center>656</y_center><phi>-0.017998707911191545</phi><theta>-0.5743224069843842</theta><w>12</w><h>16</h></bndbox></object><object><name>chair</name><pose>Unspecified</pose><truncated>0</truncated><difficult>0</difficult><bndbox><x_center>1219</x_center><y_center>616</y_center><phi>0.8459392718260016</phi><theta>-0.44342271308480924</theta><w>12</w><h>12</h></bndbox></object><object><name>chair</name><pose>Unspecified</pose><truncated>0</truncated><difficult>0</difficult><bndbox><x_center>1330</x_center><y_center>620</y_center><phi>1.2091859223973218</phi><theta>-0.4565126824747667</theta><w>12</w><h>8</h></bndbox></object><object><name>chair</name><pose>Unspecified</pose><truncated>0</truncated><difficult>0</difficult><bndbox><x_center>1292</x_center><y_center>598</y_center><phi>1.0848312131927251</phi><theta>-0.38451785083000084</theta><w>12</w><h>16</h></bndbox></object><object><name>chair</name><pose>Unspecified</pose><truncated>0</truncated><difficult>0</difficult><bndbox><x_center>1202</x_center><y_center>593</y_center><phi>0.790306901918682</phi><theta>-0.36815538909255385</theta><w>8</w><h>16</h></bndbox></object><object><name>chair</name><pose>Unspecified</pose><truncated>0</truncated><difficult>0</difficult><bndbox><x_center>1513</x_center><y_center>569</y_center><phi>1.8080520219878755</phi><theta>-0.28961557275280897</theta><w>8</w><h>8</h></bndbox></object><object><name>chair</name><pose>Unspecified</pose><truncated>0</truncated><difficult>0</difficult><bndbox><x_center>1476</x_center><y_center>540</y_center><phi>1.6869698051307689</phi><theta>-0.1947132946756175</theta><w>8</w><h>8</h></bndbox></object><object><name>chair</name><pose>Unspecified</pose><truncated>0</truncated><difficult>0</difficult><bndbox><x_center>1522</x_center><y_center>526</y_center><phi>1.8375044531152802</phi><theta>-0.14889840181076613</theta><w>8</w><h>4</h></bndbox></object><object><name>chair</name><pose>Unspecified</pose><truncated>0</truncated><difficult>0</difficult><bndbox><x_center>1578</x_center><y_center>544</y_center><phi>2.0207640245746847</phi><theta>-0.2078032640655749</theta><w>4</w><h>4</h></bndbox></object><object><name>chair</name><pose>Unspecified</pose><truncated>0</truncated><difficult>0</difficult><bndbox><x_center>1399</x_center><y_center>550</y_center><phi>1.434987894374088</phi><theta>-0.22743821815051105</theta><w>8</w><h>12</h></bndbox></object><object><name>chair</name><pose>Unspecified</pose><truncated>0</truncated><difficult>0</difficult><bndbox><x_center>1354</x_center><y_center>554</y_center><phi>1.2877257387370662</phi><theta>-0.24052818754046845</theta><w>8</w><h>12</h></bndbox></object><object><name>chair</name><pose>Unspecified</pose><truncated>0</truncated><difficult>0</difficult><bndbox><x_center>1325</x_center><y_center>542</y_center><phi>1.1928234606598744</phi><theta>-0.2012582793705962</theta><w>4</w><h>12</h></bndbox></object><object><name>chair</name><pose>Unspecified</pose><truncated>0</truncated><difficult>0</difficult><bndbox><x_center>1429</x_center><y_center>528</y_center><phi>1.5331626647987688</phi><theta>-0.15544338650574485</theta><w>8</w><h>8</h></bndbox></object><object><name>chair</name><pose>Unspecified</pose><truncated>0</truncated><difficult>0</difficult><bndbox><x_center>1392</x_center><y_center>512</y_center><phi>1.4120804479416622</phi><theta>-0.10308350894591516</theta><w>8</w><h>4</h></bndbox></object><object><name>chair</name><pose>Unspecified</pose><truncated>0</truncated><difficult>0</difficult><bndbox><x_center>1232</x_center><y_center>538</y_center><phi>0.8884816723433631</phi><theta>-0.18816830998063877</theta><w>8</w><h>8</h></bndbox></object><object><name>chair</name><pose>Unspecified</pose><truncated>0</truncated><difficult>0</difficult><bndbox><x_center>1195</x_center><y_center>540</y_center><phi>0.7673994554862571</phi><theta>-0.1947132946756175</theta><w>4</w><h>8</h></bndbox></object><object><name>chair</name><pose>Unspecified</pose><truncated>0</truncated><difficult>0</difficult><bndbox><x_center>1171</x_center><y_center>524</y_center><phi>0.6888596391465118</phi><theta>-0.14235341711578742</theta><w>4</w><h>8</h></bndbox></object><object><name>chair</name><pose>Unspecified</pose><truncated>0</truncated><difficult>0</difficult><bndbox><x_center>1211</x_center><y_center>512</y_center><phi>0.8197593330460868</phi><theta>-0.10308350894591516</theta><w>4</w><h>4</h></bndbox></object><object><name>chair</name><pose>Unspecified</pose><truncated>0</truncated><difficult>0</difficult><bndbox><x_center>1832</x_center><y_center>585</y_center><phi>2.851977080836984</phi><theta>-0.34197545031263904</theta><w>12</w><h>28</h></bndbox></object><object><name>chair</name><pose>Unspecified</pose><truncated>0</truncated><difficult>0</difficult><bndbox><x_center>1803</x_center><y_center>543</y_center><phi>2.7570748027597927</phi><theta>-0.20453077171808537</theta><w>12</w><h>28</h></bndbox></object><object><name>chair</name><pose>Unspecified</pose><truncated>0</truncated><difficult>0</difficult><bndbox><x_center>1748</x_center><y_center>809</y_center><phi>2.5770877236478773</phi><theta>-1.0750137361502572</theta><w>16</w><h>20</h></bndbox></object><object><name>window</name><pose>Unspecified</pose><truncated>0</truncated><difficult>0</difficult><bndbox><x_center>845</x_center><y_center>452</y_center><phi>-0.3779728661350221</phi><theta>0.09326603190344691</theta><w>60</w><h>16</h></bndbox></object><object><name>window</name><pose>Unspecified</pose><truncated>0</truncated><difficult>0</difficult><bndbox><x_center>1136</x_center><y_center>461</y_center><phi>0.5743224069843842</phi><theta>0.06381360077604271</theta><w>16</w><h>8</h></bndbox></object><object><name>window</name><pose>Unspecified</pose><truncated>0</truncated><difficult>0</difficult><bndbox><x_center>1658</x_center><y_center>464</y_center><phi>2.282563412373834</phi><theta>0.05399612373357464</theta><w>28</w><h>8</h></bndbox></object><object><name>window</name><pose>Unspecified</pose><truncated>0</truncated><difficult>0</difficult><bndbox><x_center>1474</x_center><y_center>463</y_center><phi>1.6804248204357903</phi><theta>0.057268616081064</theta><w>12</w><h>4</h></bndbox></object><object><name>door</name><pose>Unspecified</pose><truncated>0</truncated><difficult>0</difficult><bndbox><x_center>1762</x_center><y_center>507</y_center><phi>2.6229026165127287</phi><theta>-0.0867210472084682</theta><w>8</w><h>28</h></bndbox></object><object><name>door</name><pose>Unspecified</pose><truncated>0</truncated><difficult>0</difficult><bndbox><x_center>1409</x_center><y_center>482</y_center><phi>1.4677128178489818</phi><theta>-0.004908738521234121</theta><w>4</w><h>12</h></bndbox></object><object><name>table</name><pose>Unspecified</pose><truncated>0</truncated><difficult>0</difficult><bndbox><x_center>1271</x_center><y_center>600</y_center><phi>1.016108873895449</phi><theta>-0.39106283552497956</theta><w>28</w><h>16</h></bndbox></object><object><name>table</name><pose>Unspecified</pose><truncated>0</truncated><difficult>0</difficult><bndbox><x_center>1543</x_center><y_center>582</y_center><phi>1.9062267924125564</phi><theta>-0.33215797327017077</theta><w>16</w><h>16</h></bndbox></object><object><name>table</name><pose>Unspecified</pose><truncated>0</truncated><difficult>0</difficult><bndbox><x_center>1367</x_center><y_center>549</y_center><phi>1.3302681392544278</phi><theta>-0.22416572580302185</theta><w>16</w><h>12</h></bndbox></object><object><name>table</name><pose>Unspecified</pose><truncated>0</truncated><difficult>0</difficult><bndbox><x_center>1207</x_center><y_center>534</y_center><phi>0.8066693636561294</phi><theta>-0.17507834059068134</theta><w>16</w><h>12</h></bndbox></object></annotation>